mongorepo/__init__.py
mongorepo/_base.py
mongorepo/_common.py
mongorepo/_handlers.py
mongorepo/_methods/__init__.py
mongorepo/_methods/impl.py
mongorepo/_methods/impl_async.py
mongorepo/_methods/interfaces.py
mongorepo/classes.py
mongorepo/decorators.py
mongorepo/exceptions.py
mongorepo/implement/__init__.py
mongorepo/implement/_handlers.py
mongorepo/implement/_substitute.py
mongorepo/implement/_types.py
mongorepo/implement/_utils.py
mongorepo/implement/decorator.py
mongorepo/implement/exceptions.py
mongorepo/implement/methods.py
mongorepo/modifiers/__init__.py
mongorepo/modifiers/base.py
mongorepo/py.typed
mongorepo/queries.py
mongorepo/utils.py
mongorepo-3.1.2.dist-info/LICENSE
mongorepo-3.1.2.dist-info/METADATA
mongorepo-3.1.2.dist-info/WHEEL
mongorepo-3.1.2.dist-info/RECORD
