Metadata-Version: 2.3
Name: mongorepo
Version: 3.1.2
Summary: Simple lib that dynamically creates repositories for MongoDB
Author: artorias
Author-email: kyrylbarabash@gmail.com
Requires-Python: >=3.12,<4.0
Classifier: Programming Language :: Python :: 3
Classifier: Programming Language :: Python :: 3.12
Classifier: Programming Language :: Python :: 3.13
Requires-Dist: motor (>=3.4.0,<4.0.0)
